README.txt
setup.py
collective/__init__.py
collective.portlet.truereview.egg-info/PKG-INFO
collective.portlet.truereview.egg-info/SOURCES.txt
collective.portlet.truereview.egg-info/dependency_links.txt
collective.portlet.truereview.egg-info/entry_points.txt
collective.portlet.truereview.egg-info/namespace_packages.txt
collective.portlet.truereview.egg-info/not-zip-safe
collective.portlet.truereview.egg-info/requires.txt
collective.portlet.truereview.egg-info/top_level.txt
collective/portlet/__init__.py
collective/portlet/truereview/__init__.py
collective/portlet/truereview/configure.zcml
collective/portlet/truereview/indexer.py
collective/portlet/truereview/reviewlist.pt
collective/portlet/truereview/reviewlist.py
collective/portlet/truereview/truereview.pt
collective/portlet/truereview/truereview.py
collective/portlet/truereview/profiles/default/catalog.xml
collective/portlet/truereview/profiles/default/metadata.xml
collective/portlet/truereview/profiles/default/portlets.xml
collective/portlet/truereview/profiles/default/rolemap.xml
collective/portlet/truereview/tests/__init__.py
collective/portlet/truereview/tests/base.py
collective/portlet/truereview/tests/test_indexer.py
collective/portlet/truereview/tests/test_portlet.py
docs/HISTORY.txt
docs/INSTALL.txt
docs/LICENSE.GPL
docs/LICENSE.txt