Metadata-Version: 1.0
Name: collective.portlet.truereview
Version: 1.0b1
Summary: A review portlet that takes review permissions into account
Home-page: http://pypi.python.org/pypi/collective.portlet.truereview
Author: Martin Aspeli
Author-email: optilude@gmail.com
License: GPL
Keywords: plone portlet review
Platform: UNKNOWN
Classifier: Framework :: Plone
Classifier: Programming Language :: Python
Classifier: Topic :: Software Development :: Libraries :: Python Modules
